{
    "1054121991365468281": {
        "842106244034199572": [
            {
                "time": 1672425791,
                "issuer_id": 749443249302929479,
                "issuer_name": "Eclipse_Darkpaw#0207",
                "reason": "Fighting"
            },
            {
                "time": 1672631246,
                "issuer_id": 749443249302929479,
                "issuer_name": "Eclipse_Darkpaw#0207",
                "reason": "Fighting"
            },
            {
                "time": 1672812691,
                "issuer_id": 749443249302929479,
                "issuer_name": "Eclipse_Darkpaw#0207",
                "reason": "excessive violence and gore in RP chat"
            },
            {
                "time": 1672812778,
                "issuer_id": 749443249302929479,
                "issuer_name": "Eclipse_Darkpaw#0207",
                "reason": "excessive violence in <#1054137434725691393>"
            },
            {
                "time": 1675905528,
                "issuer_id": 749443249302929479,
                "issuer_name": "Eclipse_Darkpaw#0207",
                "reason": "Discussing topics that are too heavy in general chat"
            },
            {
                "time": 1675909046,
                "issuer_id": 626455771441266707,
                "issuer_name": "Zenith#1234",
                "reason": "didn't change since last time"
            },
            {
                "time": 1676067446,
                "issuer_id": 749443249302929479,
                "issuer_name": "Eclipse_Darkpaw#0207",
                "reason": "posting intentionally disturbing images in <#1054137434725691393>"
            },
            {
                "time": 1676072532,
                "issuer_id": 749443249302929479,
                "issuer_name": "Eclipse_Darkpaw#0207",
                "reason": "posting gory/disturbing content in suspended chat"
            }
        ],
        "782400723853246484": [],
        "422376785116790814": [
            {
                "time": 1672969159,
                "issuer_id": 749443249302929479,
                "issuer_name": "Eclipse_Darkpaw#0207",
                "reason": "posting disturbing content in <#1057821464721621133>"
            }
        ],
        "1028734945256018000": [
            {
                "time": 1674257284,
                "issuer_id": 966409366108532828,
                "issuer_name": "RZ54#5031",
                "reason": "Weird post in general"
            },
            {
                "time": 1674317308,
                "issuer_id": 749443249302929479,
                "issuer_name": "Eclipse_Darkpaw#0207",
                "reason": "postin inappropriate memes in <#1054216785194405959>"
            }
        ],
        "905529060522864640": [
            {
                "time": 1674880819,
                "issuer_id": 749443249302929479,
                "issuer_name": "Eclipse_Darkpaw#0207",
                "reason": "Please dont post excessively gorey content in chat"
            }
        ],
        "1061368056288383047": [
            {
                "time": 1675475847,
                "issuer_id": 966409366108532828,
                "issuer_name": "RZ54#5031",
                "reason": "Nonsensical video in general"
            },
            {
                "time": 1676664997,
                "issuer_id": 749443249302929479,
                "issuer_name": "Eclipse_Darkpaw#0207",
                "reason": "asking a moderator to send violent content"
            }
        ],
        "434480702747181056": [
            {
                "time": 1675905075,
                "issuer_id": 749443249302929479,
                "issuer_name": "Eclipse_Darkpaw#0207",
                "reason": "Kinkshaming"
            }
        ],
        "334646324962263041": [],
        "546894704730439683": [
            {
                "time": 1676825091,
                "issuer_id": 749443249302929479,
                "issuer_name": "Eclipse_Darkpaw#0207",
                "reason": "please do not post cub porn in the server"
            }
        ],
        "1041383586403721258": [
            {
                "time": 1676929542,
                "issuer_id": 749443249302929479,
                "issuer_name": "Eclipse_Darkpaw#0207",
                "reason": "fighting the mods"
            }
        ],
        "749443249302929479": [],
        "844737544620474439": [
            {
                "time": 1680133221,
                "issuer_id": 749443249302929479,
                "issuer_name": "Eclipse_Darkpaw#0207",
                "reason": "please dont erp with other users without asking to first."
            }
        ],
        "327587514896351232": [
            {
                "time": 1680302124,
                "issuer_id": 782400723853246484,
                "issuer_name": "Wicc\u26a1#7678",
                "reason": " drama in gallery channel"
            }
        ],
        "260220437265383425": [
            {
                "time": 1680673055,
                "issuer_id": 749443249302929479,
                "issuer_name": "Eclipse_Darkpaw#0207",
                "reason": "please don't dont post a video where people get lit on fire"
            }
        ],
        "472902007917772811": [
            {
                "time": 1680979972,
                "issuer_id": 782400723853246484,
                "issuer_name": "Wicc\u26a1#7678",
                "reason": "random, nonconsensual roleplay in DMs"
            }
        ],
        "979141701895602218": [
            {
                "time": 1683916296,
                "issuer_id": 749443249302929479,
                "issuer_name": "Eclipse_Darkpaw#0207",
                "reason": "please don't try and ruin someones kink by bringing up how implausible it is irl and how it would kill them"
            }
        ],
        "891173641310597172": [
            {
                "time": 1684006800,
                "issuer_id": 749443249302929479,
                "issuer_name": "Eclipse_Darkpaw#0207",
                "reason": "please read user bios before DMing or friend requesting"
            },
            {
                "time": 1684006835,
                "issuer_id": 749443249302929479,
                "issuer_name": "Eclipse_Darkpaw#0207",
                "reason": "do not enter user DMs and ask for a private video call"
            }
        ],
        "372809710648164352": [
            {
                "time": 1686004012,
                "issuer_id": 749443249302929479,
                "issuer_name": "Eclipse_Darkpaw#6576",
                "reason": " do not post animals being killed in <#1054216785194405959>"
            }
        ],
        "968659972999229474": [
            {
                "time": 1686851218,
                "issuer_id": 749443249302929479,
                "issuer_name": "Eclipse_Darkpaw#6576",
                "reason": "keep ads to <#1054475673252679701> and out of <#1054137434725691393>"
            }
        ],
        "784476086150103061": [
            {
                "time": 1689962898,
                "issuer_id": 749443249302929479,
                "issuer_name": "autumnal.equinox#0",
                "reason": "dont post media with racial slurs"
            }
        ],
        "780944067768483880": [
            {
                "time": 1689982247,
                "issuer_id": 749443249302929479,
                "issuer_name": "autumnal.equinox#0",
                "reason": "please do not post videos about questionable topics"
            }
        ],
        "403253406896095232": [
            {
                "time": 1691951448,
                "issuer_id": 782400723853246484,
                "issuer_name": "anamasu1204#0",
                "reason": "fighting with mod, restarting drama that had already ended"
            }
        ],
        "1149502160699130038": [
            {
                "time": 1695177156,
                "issuer_id": 749443249302929479,
                "issuer_name": "autumnal.equinox#0",
                "reason": " Ban evasion"
            },
            {
                "time": 1695177302,
                "issuer_id": 749443249302929479,
                "issuer_name": "autumnal.equinox#0",
                "reason": "alt of <@1139940317676720228>"
            },
            {
                "time": 1695177419,
                "issuer_id": 749443249302929479,
                "issuer_name": "autumnal.equinox#0",
                "reason": "im letting the bot create the thread"
            }
        ],
        "948692688469893160": [
            {
                "time": 1697214585,
                "issuer_id": 749443249302929479,
                "issuer_name": "autumnal.equinox",
                "reason": "do not put children in nsfw channels"
            }
        ],
        "313140388796039178": [
            {
                "time": 1698814770,
                "issuer_id": 749443249302929479,
                "issuer_name": "autumnal.equinox",
                "reason": "Do not ask to ERP with people who have already said no. use <#1057000875731718254>"
            }
        ],
        "513297683142934530": [
            {
                "time": 1699981023,
                "issuer_id": 749443249302929479,
                "issuer_name": "autumnal.equinox",
                "reason": "Do not post gore in chat"
            }
        ],
        "1127589891010744401": [
            {
                "time": 1700015409,
                "issuer_id": 749443249302929479,
                "issuer_name": "autumnal.equinox",
                "reason": " Do not promote your stream in <#1054137434725691393>, please keep it in <#1054475673252679701> or <#1146438044094824449>"
            }
        ],
        "1037894076453879919": [
            {
                "time": 1703623337,
                "issuer_id": 749443249302929479,
                "issuer_name": "autumnal.equinox",
                "reason": "do not use transphobic terms to describe trans people"
            },
            {
                "time": 1703623363,
                "issuer_id": 749443249302929479,
                "issuer_name": "autumnal.equinox",
                "reason": "please use chats for what they are meant for"
            }
        ]
    }
}